picosoc/circuit.v
module circuit (
  input clk,
  input resetn,

  input [3:0]   reg_seed_we,
  input [31:0]  reg_seed_di,
  output [31:0] reg_seed_do,

  input         reg_dat_we,
  input         reg_dat_re,
  input  [31:0] reg_dat_di,
  output [31:0] reg_dat_do,
  output        reg_dat_wait
);
reg fini;
reg [31:0] seed;
reg [1:0] state;
reg [31:0] compteur;
reg [31:0] lfsr;
reg seed_modifie = 0;

assign reg_dat_wait = !fini;
assign reg_dat_do = lfsr; 
assign reg_seed_do = seed;
// wire bit_lfsr = lfsr[31] ^ lfsr[21] ^ lfsr[1] ^ lfsr[0];
wire bit_lfsr = lfsr[31] + lfsr[0];
always @(posedge clk) begin
  if (!resetn) begin
    seed <= 32'h dead_beef;
    seed_modifie <= 0;
  end else begin
    if (reg_seed_we[0]) seed[ 7: 0] <= reg_seed_di[ 7: 0];
    if (reg_seed_we[1]) seed[15: 8] <= reg_seed_di[15: 8];
    if (reg_seed_we[2]) seed[23:16] <= reg_seed_di[23:16];
    if (reg_seed_we[3]) seed[31:24] <= reg_seed_di[31:24];
    if (reg_seed_we != 4'b 0000) seed_modifie <= 1;
    else seed_modifie <= 0;
  end
end

// reg [31:0] sum;
// always @(posedge clk) begin
//   if (!resetn) begin
//     sum <= 0;
//   end else begin
//     if (reg_dat_re) begin
//       // sum <= 1 + 2;
//       sum <= reg_dat_di + reg_seed_di;
//     end
//   end
// end
// assign reg_dat_do = sum;

always @(posedge clk) begin
  if (!resetn) begin
    fini <= 0;
    state <= 0;
    compteur <= 0;
    lfsr <= seed;
  end
  case(state)
    0: begin
      if (seed_modifie) begin
        lfsr <= seed;
      end
      if (reg_dat_re) begin
        state <= 1;
        compteur <= 0;
        fini <= 0;
      end
    end 
    1: begin 
    compteur <= compteur +1;
    // lfsr <= {lfsr[30:0],bit_lfsr};
    lfsr <= lfsr + 1;
    if (compteur == 0) begin 
      state <= 2;
    end
  end
  2: begin
    fini <= 1;
    state <= 0;
  end
  default: begin
    state <= 0;
    fini <= 1;
  end
endcase
    end

endmodule

picosoc/lfsr_tb.v
`include "circuit.v"

`timescale 1ns / 1ps

module lfsr_tb();
reg clock;
reg resetn;

// Pour le poistionnement du seed
reg [3:0] seed_we;
reg [31:0] seed_in;
wire [31:0] seed_out;

// Pour les échanges sur le bus de données
reg data_we;
reg data_re;
reg [31:0] data_in;
wire [31:0] data_out;
wire data_wait;

// Device Under Test
circuit dut(.clk(clock),.resetn(resetn),
            .reg_seed_we(seed_we), .reg_seed_di(seed_in), .reg_seed_do(seed_out),
            .reg_dat_we(data_we), .reg_dat_re(data_re), .reg_dat_di(data_in), .reg_dat_do(data_out),
            .reg_dat_wait(data_wait));


// Génération du signal d'horloge
initial begin
  clock = 1;
  forever #5 clock <= ~clock;
end

//Génération du signal de reset
initial begin
  resetn = 1;
  #5 resetn = 0;
  #5 resetn = 1;
end

initial begin
  $dumpfile("lfsr.vcd");
  $dumpvars(0, dut);
  #10 seed_we = 4'b 1111;
  seed_in = 32'h babecafe;
  #20 seed_we = 4'b 0000;
  data_re = 4'b 1111;
  #350 $finish;
end
endmodule

picosoc/lfsr.vcd
$date
	Thu Apr 18 01:30:47 2024
$end
$version
	Icarus Verilog
$end
$timescale
	1ps
$end
$scope module lfsr_tb $end
$scope module dut $end
$var wire 1 ! bit_lfsr $end
$var wire 1 " clk $end
$var wire 32 # reg_dat_di [31:0] $end
$var wire 32 $ reg_dat_do [31:0] $end
$var wire 1 % reg_dat_re $end
$var wire 1 & reg_dat_we $end
$var wire 32 ' reg_seed_di [31:0] $end
$var wire 32 ( reg_seed_do [31:0] $end
$var wire 4 ) reg_seed_we [3:0] $end
$var wire 1 * resetn $end
$var wire 1 + reg_dat_wait $end
$var reg 32 , compteur [31:0] $end
$var reg 1 - fini $end
$var reg 32 . lfsr [31:0] $end
$var reg 32 / seed [31:0] $end
$var reg 1 0 seed_modifie $end
$var reg 2 1 state [1:0] $end
$upscope $end
$upscope $end
$enddefinitions $end
#0
$dumpvars
b0 1
00
bx /
bx .
1-
bx ,
0+
1*
bx )
bx (
bx '
x&
x%
bx $
bx #
1"
x!
$end
#5000
0"
0*
#10000
10
b10111010101111101100101011111110 (
b10111010101111101100101011111110 /
1"
1*
b10111010101111101100101011111110 '
b1111 )
#15000
0"
#20000
1!
b10111010101111101100101011111110 $
b10111010101111101100101011111110 .
1"
#25000
0"
#30000
1+
0-
b0 ,
b1 1
00
1"
1%
b0 )
#35000
0"
#40000
0!
b1110101011111011001010111111101 $
b1110101011111011001010111111101 .
b1 ,
1"
#45000
0"
#50000
1!
b11101010111110110010101111111010 $
b11101010111110110010101111111010 .
b10 ,
1"
#55000
0"
#60000
1!
b11010101111101100101011111110101 $
b11010101111101100101011111110101 .
b11 ,
1"
#65000
0"
#70000
0!
b10101011111011001010111111101011 $
b10101011111011001010111111101011 .
b100 ,
1"
#75000
0"
#80000
1!
b1010111110110010101111111010110 $
b1010111110110010101111111010110 .
b101 ,
1"
#85000
0"
#90000
1!
b10101111101100101011111110101101 $
b10101111101100101011111110101101 .
b110 ,
1"
#95000
0"
#100000
1!
b1011111011001010111111101011011 $
b1011111011001010111111101011011 .
b111 ,
1"
#105000
0"
#110000
b10111110110010101111111010110111 $
b10111110110010101111111010110111 .
b1000 ,
1"
#115000
0"
#120000
0!
b1111101100101011111110101101111 $
b1111101100101011111110101101111 .
b1001 ,
1"
#125000
0"
#130000
1!
b11111011001010111111101011011110 $
b11111011001010111111101011011110 .
b1010 ,
1"
#135000
0"
#140000
0!
b11110110010101111111010110111101 $
b11110110010101111111010110111101 .
b1011 ,
1"
#145000
0"
#150000
1!
b11101100101011111110101101111010 $
b11101100101011111110101101111010 .
b1100 ,
1"
#155000
0"
#160000
0!
b11011001010111111101011011110101 $
b11011001010111111101011011110101 .
b1101 ,
1"
#165000
0"
#170000
1!
b10110010101111111010110111101010 $
b10110010101111111010110111101010 .
b1110 ,
1"
#175000
0"
#180000
0!
b1100101011111110101101111010101 $
b1100101011111110101101111010101 .
b1111 ,
1"
#185000
0"
#190000
1!
b11001010111111101011011110101010 $
b11001010111111101011011110101010 .
b10000 ,
1"
#195000
0"
#200000
1!
b10010101111111010110111101010101 $
b10010101111111010110111101010101 .
b10001 ,
1"
#205000
0"
#210000
1!
b101011111110101101111010101011 $
b101011111110101101111010101011 .
b10010 ,
1"
#215000
0"
#220000
b1010111111101011011110101010111 $
b1010111111101011011110101010111 .
b10011 ,
1"
#225000
0"
#230000
0!
b10101111111010110111101010101111 $
b10101111111010110111101010101111 .
b10100 ,
1"
#235000
0"
#240000
1!
b1011111110101101111010101011110 $
b1011111110101101111010101011110 .
b10101 ,
1"
#245000
0"
#250000
1!
b10111111101011011110101010111101 $
b10111111101011011110101010111101 .
b10110 ,
1"
#255000
0"
#260000
0!
b1111111010110111101010101111011 $
b1111111010110111101010101111011 .
b10111 ,
1"
#265000
0"
#270000
1!
b11111110101101111010101011110110 $
b11111110101101111010101011110110 .
b11000 ,
1"
#275000
0"
#280000
1!
b11111101011011110101010111101101 $
b11111101011011110101010111101101 .
b11001 ,
1"
#285000
0"
#290000
1!
b11111010110111101010101111011011 $
b11111010110111101010101111011011 .
b11010 ,
1"
#295000
0"
#300000
0!
b11110101101111010101011110110111 $
b11110101101111010101011110110111 .
b11011 ,
1"
#305000
0"
#310000
1!
b11101011011110101010111101101110 $
b11101011011110101010111101101110 .
b11100 ,
1"
#315000
0"
#320000
1!
b11010110111101010101111011011101 $
b11010110111101010101111011011101 .
b11101 ,
1"
#325000
0"
#330000
0!
b10101101111010101011110110111011 $
b10101101111010101011110110111011 .
b11110 ,
1"
#335000
0"
#340000
1!
b1011011110101010111101101110110 $
b1011011110101010111101101110110 .
b11111 ,
1"
#345000
0"
#350000
1!
b10 1
b10110111101010101111011011101101 $
b10110111101010101111011011101101 .
b100000 ,
1"
#355000
0"
#360000
b0 1
0+
1-
1"
#365000
0"
#370000
1+
0-
b0 ,
b1 1
1"
#375000
0"
#380000
0!
b1101111010101011110110111011011 $
b1101111010101011110110111011011 .
b1 ,
1"
